fingerprintLAB/__init__.py
fingerprintLAB/enhancement/__init__.py
fingerprintLAB/enhancement/frequency.py
fingerprintLAB/enhancement/spatial.py
fingerprintLAB/intrinsic/__init__.py
fingerprintLAB/intrinsic/frequency/__init__.py
fingerprintLAB/intrinsic/frequency/projection.py
fingerprintLAB/intrinsic/frequency/tools.py
fingerprintLAB/intrinsic/mask/__init__.py
fingerprintLAB/intrinsic/multiple/__init__.py
fingerprintLAB/intrinsic/multiple/transform.py
fingerprintLAB/intrinsic/orientation/__init__.py
fingerprintLAB/intrinsic/orientation/gradient.py
fingerprintLAB/intrinsic/orientation/tools.py
fingerprintLAB/matching/__init__.py
fingerprintLAB/matching/matching.py
fingerprintLAB/minutiae/__init__.py
fingerprintLAB/tools/__init__.py
fingerprintLAB/tools/array.py
fingerprintLAB/tools/image.py
fingerprintLAB/tools/nbis.py
fingerprintLAB/tools/tensor.py
tests/__init__.py
fingerprintLAB-0.0.1.dist-info/LICENSE.txt
fingerprintLAB-0.0.1.dist-info/METADATA
fingerprintLAB-0.0.1.dist-info/WHEEL
fingerprintLAB-0.0.1.dist-info/top_level.txt
fingerprintLAB-0.0.1.dist-info/RECORD
